Tool.py
testlib/__init__.py
testlib/testlibone.py
wcltestlib-1.0.1.dist-info/LICENSE.txt
wcltestlib-1.0.1.dist-info/METADATA
wcltestlib-1.0.1.dist-info/WHEEL
wcltestlib-1.0.1.dist-info/top_level.txt
wcltestlib-1.0.1.dist-info/RECORD
