Metadata-Version: 2.1
Name: wcltestlib
Version: 1.0.1
Summary: this is a testlib
Home-page: https://github.com/wcl1997/PythonCode
Author: wcl
Author-email: wcl0729@163.com
License: MIT
Platform: UNKNOWN
